burtle/__init__.py
burtle/burtle.py
burtle/function_events.py
burtle/globals.py
burtle/gravity.py
burtle/key_binding.py
burtle/logic.py
burtle/textbox.py
burtle/window.py
burtle/default_images/black_circle.gif
burtle/default_images/black_rectangle.gif
burtle/default_images/white_circle.gif
burtle/default_images/white_rectangle.gif
burtle-1.4.dist-info/METADATA
burtle-1.4.dist-info/WHEEL
burtle-1.4.dist-info/top_level.txt
burtle-1.4.dist-info/RECORD
