Metadata-Version: 2.1
Name: burtle
Version: 1.4
Summary: A game focued version of the turtle module
Home-page: https://github.com/alannxq/Burtle
Author: Alan Koterba
Author-email: alankoterba12321@gmail.com
License: MIT
Keywords: turtle,burtle,game
Platform: UNKNOWN
Classifier: Development Status :: 3 - Alpha
Classifier: Intended Audience :: Developers
Classifier: Topic :: Software Development :: Build Tools
Classifier: License :: OSI Approved :: MIT License
Classifier: Programming Language :: Python :: 3
Classifier: Programming Language :: Python :: 3.4
Classifier: Programming Language :: Python :: 3.5
Classifier: Programming Language :: Python :: 3.6
Requires-Dist: pillow
Requires-Dist: pygame
Requires-Dist: keyboard
